{
    "appTitle": "Hablas",
    "login": "Log masuk",
    "signup": "Daftar",
    "dailyPages": "Halaman harian",
    "freeRead": "Baca percuma",
    "pleaseLoginToStart": "Sila log masuk untuk memulakan",
    "email": "E -mel",
    "password": "Kata laluan",
    "settings": "Tetapan",
    "switchToMode": "Beralih ke",
    "nativeLanguage": "Bahasa ibunda",
    "tutorial": "Tutorial",
    "supportHablas": "Sokongan Hablas",
    "foundABug": "Menjumpai pepijat",
    "sendingBugReport": "Menghantar laporan bug ...",
    "bugReportSent": "Laporan bug dihantar!Terima kasih kerana membantu kami memperbaiki.",
    "bugReportError": "Ralat menghantar laporan bug.Sila cuba lagi.",
    "tapToBegin": "Ketik di sini untuk memulakan!",
    "selectPagele": "Pilih Pagele",
    "chapters": "Bab",
    "translate": "Terjemahkan",
    "loading": "Memuatkan ...",
    "translating": "Menterjemahkan ...",
    "processing": "Memproses ...",
    "fetchingData": "Mengambil data ...",
    "parsingData": "Data parsing ...",
    "loadMore": "Memuat lebih banyak",
    "chapterTitle": "Tajuk Bab",
    "points": "Mata",
    "prevSentence": "Sebelumnya",
    "nextSentence": "Seterusnya",
    "loggedInAs": "Log masuk sebagai",
    "logout": "Logout",
    "changeInfo": "Tukar maklumat",
    "deleteAccount": "Padam akaun",
    "userAccountOptions": "Pilihan akaun pengguna",
    "completeYourTip": "Lengkapkan hujung anda",
    "payNow": "Bayar sekarang",
    "customAmount": "Jumlah tersuai",
    "tip": "Petua",
    "thankYouForTip": "Terima kasih atas tip anda!",
    "invalidCredentials": "Kelayakan tidak sah, adakah anda mendaftar?",
    "sessionExpired": "Sesi anda telah tamat.Sila log masuk lagi.",
    "enterValidEmail": "Sila masukkan alamat e -mel yang sah",
    "passwordCannotBeEmpty": "Kata laluan tidak boleh kosong",
    "microphonePermissionRequired": "Kebenaran mikrofon diperlukan untuk rakaman.",
    "couldNotAccessMicrophone": "Tidak dapat mengakses mikrofon.Sila periksa kebenaran penyemak imbas anda.",
    "failedToStartRecording": "Gagal memulakan rakaman.Sila cuba lagi.",
    "enterValidAmount": "Sila masukkan jumlah yang sah",
    "errorLoadingTutorial": "Kandungan Tutorial Memuat Ralat",
    "pleaseTryAgain": "Sila cuba lagi kemudian.",
    "noSentencesAvailable": "Tiada ayat yang tersedia untuk bab ini.",
    "noChaptersAvailable": "Tiada bab yang tersedia.",
    "noPageleBooksAvailable": "Tiada buku Pagele yang tersedia.",
    "reachedEndOfBook": "Mencapai akhir buku",
    "errorRenderingBook": "Buku rendering ralat",
    "errorProcessingTip": "Petua pemprosesan ralat.Sila cuba lagi."
}